MANIFEST.in
README.rst
setup.py
meditate/__init__.py
meditate.egg-info/PKG-INFO
meditate.egg-info/SOURCES.txt
meditate.egg-info/dependency_links.txt
meditate.egg-info/entry_points.txt
meditate.egg-info/requires.txt
meditate.egg-info/top_level.txt
meditate/data/sound/140128__jetrye__bell-meditation-cleaned.wav