Metadata-Version: 1.2
Name: meditate
Version: 1.0.1
Summary: A command line meditation clock.
Home-page: https://gitlab.com/yuvallanger/meditate
Author: Yuval Langer
Author-email: yuval.langer@gmail.com
Maintainer: Yuval Langer
Maintainer-email: yuval.langer@gmail.com
License: AGPL-3.0-or-later
Project-URL: Source, https://gitlab.com/yuvallanger/meditate
Project-URL: Tracker, https://gitlab.com/yuvallanger/meditate/issues
Project-URL: BitBucket Mirror, https://bitbucket.org/yuvallanger/meditate
Project-URL: GitGud Mirror, https://gitgud.io/yuvallanger/meditate
Project-URL: GitHub Mirror, https://github.com/yuvallanger/meditate
Keywords: meditation
Platform: UNKNOWN
Classifier: Environment :: Console
Classifier: Framework :: Trio
Classifier: License :: OSI Approved :: GNU Affero General Public License v3 or later (AGPLv3+)
Classifier: Programming Language :: Python :: 3.6
Requires-Python: ~=3.5
